infi.clickhouse_fdw-0.5.1-py2.7-nspkg.pth
infi/clickhouse_fdw/__init__.py
infi/clickhouse_fdw/__version__.py
infi/clickhouse_fdw/generate.py
infi/clickhouse_fdw/main.py
infi.clickhouse_fdw-0.5.1.dist-info/DESCRIPTION.rst
infi.clickhouse_fdw-0.5.1.dist-info/METADATA
infi.clickhouse_fdw-0.5.1.dist-info/RECORD
infi.clickhouse_fdw-0.5.1.dist-info/WHEEL
infi.clickhouse_fdw-0.5.1.dist-info/entry_points.txt
infi.clickhouse_fdw-0.5.1.dist-info/metadata.json
infi.clickhouse_fdw-0.5.1.dist-info/namespace_packages.txt
infi.clickhouse_fdw-0.5.1.dist-info/top_level.txt
