Metadata-Version: 2.0
Name: infi.clickhouse-fdw
Version: 0.5.1
Summary: A PostgreSQL foreign data wrapper for ClickHouse
Home-page: https://github.com/Infinidat/infi.clickhouse_fdw
Author: Itai Shirav
Author-email: itais@infinidat.com
License: BSD
Platform: UNKNOWN
Classifier: Intended Audience :: Developers
Classifier: Intended Audience :: System Administrators
Classifier: License :: OSI Approved :: BSD License
Classifier: Operating System :: OS Independent
Classifier: Programming Language :: Python
Classifier: Topic :: Software Development :: Libraries :: Python Modules
Requires-Dist: click
Requires-Dist: colorama
Requires-Dist: infi.clickhouse-orm
Requires-Dist: pygments
Requires-Dist: setuptools
